genome/__init__.py
genome/rename_genome_id.py
genome/split_bed_fai_by_number.py
genome/docs/rename-genome-id.md
genome/tests/__init__.py
genome/tests/test_rename_genome_id.py
genome/tests/test_split_bed_fai_by_number.py
liftover/__init__.py
liftover/liftover_flank_and_site.py
liftover/tests/__init__.py
liftover/tests/test_liftover_flank_and_site.py
vcf/__init__.py
vcf/table2vcf.py
vcf/tests/__init__.py
vcf/tests/test_table2vcf.py
tc_pytools-1.1.5.dist-info/METADATA
tc_pytools-1.1.5.dist-info/WHEEL
tc_pytools-1.1.5.dist-info/entry_points.txt
tc_pytools-1.1.5.dist-info/licenses/LICENSE
tc_pytools-1.1.5.dist-info/RECORD
