Metadata-Version: 2.4
Name: tc-pytools
Version: 1.1.5
Summary: Toolkit for processing genomic data files
Project-URL: Homepage, https://github.com/bioShaun/tc-pytools-v2
Project-URL: Documentation, https://github.com/bioShaun/tc-pytools-v2/blob/main/README.md
Project-URL: Repository, https://github.com/bioShaun/tc-pytools-v2
Project-URL: Issues, https://github.com/bioShaun/tc-pytools-v2/issues
Project-URL: Changelog, https://github.com/bioShaun/tc-pytools-v2/blob/main/CHANGELOG.md
Author-email: lx Gui <ricekent@163.com>
Maintainer-email: lx Gui <ricekent@163.com>
License: MIT
License-File: LICENSE
Keywords: FASTA,GFF,NCBI,NGDC,bioinformatics,genomics
Classifier: Development Status :: 4 - Beta
Classifier: Intended Audience :: Science/Research
Classifier: License :: OSI Approved :: MIT License
Classifier: Operating System :: OS Independent
Classifier: Programming Language :: Python :: 3
Classifier: Programming Language :: Python :: 3.10
Classifier: Programming Language :: Python :: 3.11
Classifier: Programming Language :: Python :: 3.12
Classifier: Programming Language :: Python :: 3.13
Classifier: Topic :: Scientific/Engineering :: Bio-Informatics
Requires-Python: >=3.8
Requires-Dist: loguru>=0.7.0
Requires-Dist: pandas>=1.5.0
Requires-Dist: requests>=2.0.0
Requires-Dist: tqdm>=4.0.0
Requires-Dist: typer>=0.9.0
Requires-Dist: typing-extensions>=4.0.0
